{"type": "Feature", "id": 12513024, "properties": {"woe:id": 12513024, "woe:parent_id": 1333004, "woe:name": "Sunyani Airport", "woe:placetype": 14, "woe:placetype_name": "Airport", "woe:lang": "ENG", "iso:country": "GH", "meta:provider": ["geoplanet:7.3.1", "geoplanet:7.3.2", "geoplanet:7.4.0", "geoplanet:7.4.1", "geoplanet:7.5.1", "geoplanet:7.5.2", "geoplanet:7.6.0", "geoplanet:7.8.1", "geoplanet:7.9.0", "geoplanet:7.10.0", "geoplanet:8.0.0", "woeplanet:8.0.0"], "meta:indexed": "2020-08-20T20:21:19.489352", "woe:alias_ENG_V": ["NYI Airport", "NYI"], "meta:updated": "2020-08-22T02:49:21.019666", "woe:hierarchy": {"continent": 24865670, "country": 23424824, "town": 0, "planet": 1, "county": 0, "suburb": 0, "state": 2345464, "region": 0, "localadmin": 0}, "woe:timezone_id": 28350682, "woe:hash": "ecq3gj54ns6j", "woe:centroid": [-2.3247, 7.3667], "geom:latitude": 7.3667, "geom:longitude": -2.3247, "geom:hash": "ecq3gj54ns6j", "woe:latitude": 7.3667, "geom:centroid": [-2.3247, 7.3667], "woe:longitude": -2.3247, "woe:repo": "woeplanet-airport-gh"}, "geometry": {"coordinates": [-2.3247, 7.3667], "type": "Point"}}